HISTORY.txt
LICENSE.txt
MANIFEST.in
README.rst
TODO.txt
setup.cfg
setup.py
src/iroin_pycountry/__init__.py
src/iroin_pycountry/db.py
src/iroin_pycountry.egg-info/PKG-INFO
src/iroin_pycountry.egg-info/SOURCES.txt
src/iroin_pycountry.egg-info/dependency_links.txt
src/iroin_pycountry.egg-info/not-zip-safe
src/iroin_pycountry.egg-info/requires.txt
src/iroin_pycountry.egg-info/top_level.txt
src/iroin_pycountry/tests/test_general.py